<?xml version="1.0" encoding="utf-8"?>
<ArrayOfOrder xmlns:xsi="http://www.w3.org/2001/XMLSchema-instance" xmlns:xsd="http://www.w3.org/2001/XMLSchema">
  <Order>
    <ID>1001</ID>
    <CustomerName>Motti Weiss</CustomerName>
    <CustomerEmail>MottiWeiss@gmail.com</CustomerEmail>
    <CustomerAdress>Chazon Ish 3 Beit Shemesh</CustomerAdress>
    <CreateOrderDate>2021-03-07T12:00:56</CreateOrderDate>
    <ShippingDate>2021-03-09T12:00:56</ShippingDate>
    <DeliveryDate>2021-03-11T12:00:56</DeliveryDate>
  </Order>
  <Order>
    <ID>1002</ID>
    <CustomerName>Moshe Feld</CustomerName>
    <CustomerEmail>MosheFeld@gmail.com</CustomerEmail>
    <CustomerAdress>Rabbi Akiva 170 Bnei Brak</CustomerAdress>
    <CreateOrderDate>2015-11-20T04:51:11</CreateOrderDate>
    <ShippingDate>2015-11-24T04:51:11</ShippingDate>
    <DeliveryDate>2015-11-24T04:51:11</DeliveryDate>
  </Order>
  <Order>
    <ID>1003</ID>
    <CustomerName>Itzik Orlev</CustomerName>
    <CustomerEmail>ItzikOrlev@gmail.com</CustomerEmail>
    <CustomerAdress>Hakalanit 17 herzelia</CustomerAdress>
    <CreateOrderDate>2013-05-24T19:23:37</CreateOrderDate>
    <ShippingDate>2013-05-25T19:23:37</ShippingDate>
    <DeliveryDate>2013-05-29T19:23:37</DeliveryDate>
  </Order>
  <Order>
    <ID>1004</ID>
    <CustomerName>Ruli Dikman</CustomerName>
    <CustomerEmail>RuliDikman@gmail.com</CustomerEmail>
    <CustomerAdress>Haturim 6 Jerusalem</CustomerAdress>
    <CreateOrderDate>2006-04-12T00:38:33</CreateOrderDate>
    <ShippingDate>2006-04-14T00:38:33</ShippingDate>
    <DeliveryDate>2006-04-15T00:38:33</DeliveryDate>
  </Order>
  <Order>
    <ID>1005</ID>
    <CustomerName>Ari Hill</CustomerName>
    <CustomerEmail>AriHill@gmail.com</CustomerEmail>
    <CustomerAdress>Malchei Israel 40 Jerusalem</CustomerAdress>
    <CreateOrderDate>2005-12-08T08:56:18</CreateOrderDate>
    <ShippingDate>2005-12-17T08:56:18</ShippingDate>
    <DeliveryDate>2005-12-10T08:56:18</DeliveryDate>
  </Order>
  <Order>
    <ID>1006</ID>
    <CustomerName>Shuli Rand</CustomerName>
    <CustomerEmail>ShuliRand@gmail.com</CustomerEmail>
    <CustomerAdress>miron 20 Bnei Brak</CustomerAdress>
    <CreateOrderDate>2001-03-16T23:22:11</CreateOrderDate>
    <ShippingDate>2001-03-18T23:22:11</ShippingDate>
    <DeliveryDate>2001-03-22T23:22:11</DeliveryDate>
  </Order>
  <Order>
    <ID>1007</ID>
    <CustomerName>Ishay Ribo</CustomerName>
    <CustomerEmail>IshayRibo@gmail.com</CustomerEmail>
    <CustomerAdress>Hameiri 4 Jerusalem</CustomerAdress>
    <CreateOrderDate>2014-02-25T13:47:04</CreateOrderDate>
    <ShippingDate>2014-02-28T13:47:04</ShippingDate>
    <DeliveryDate>2014-03-04T13:47:04</DeliveryDate>
  </Order>
  <Order>
    <ID>1008</ID>
    <CustomerName>Beri Weber</CustomerName>
    <CustomerEmail>BeriWeber@gmail.com</CustomerEmail>
    <CustomerAdress>begin 72 Naaria</CustomerAdress>
    <CreateOrderDate>2009-05-15T10:58:54</CreateOrderDate>
    <ShippingDate>2009-05-19T10:58:54</ShippingDate>
    <DeliveryDate>2009-05-18T10:58:54</DeliveryDate>
  </Order>
  <Order>
    <ID>1009</ID>
    <CustomerName>Simcha Friedman</CustomerName>
    <CustomerEmail>SimchaFriedman@gmail.com</CustomerEmail>
    <CustomerAdress>hagefen 22 Kfar Chabad</CustomerAdress>
    <CreateOrderDate>2000-08-14T05:50:45</CreateOrderDate>
    <ShippingDate>2000-08-18T05:50:45</ShippingDate>
    <DeliveryDate>2023-02-26T14:47:05.350663+02:00</DeliveryDate>
  </Order>
  <Order>
    <ID>1010</ID>
    <CustomerName>Avraam Fried</CustomerName>
    <CustomerEmail>AvraamFried@gmail.com</CustomerEmail>
    <CustomerAdress>hanurit 7 Ashdod</CustomerAdress>
    <CreateOrderDate>2011-01-14T03:22:30</CreateOrderDate>
    <ShippingDate>2011-01-21T03:22:30</ShippingDate>
    <DeliveryDate>2023-02-26T14:47:24.3487473+02:00</DeliveryDate>
  </Order>
  <Order>
    <ID>1011</ID>
    <CustomerName>Mordechai Ben David</CustomerName>
    <CustomerEmail>MordechaiBenDavid@gmail.com</CustomerEmail>
    <CustomerAdress>Shamgar 20 Jerusalem</CustomerAdress>
    <CreateOrderDate>2015-07-22T23:37:35</CreateOrderDate>
    <ShippingDate>2015-07-24T23:37:35</ShippingDate>
    <DeliveryDate>2023-02-26T14:47:34.7036753+02:00</DeliveryDate>
  </Order>
  <Order>
    <ID>1012</ID>
    <CustomerName>Yaakov Shwekey</CustomerName>
    <CustomerEmail>YaakovShwekey@gmail.com</CustomerEmail>
    <CustomerAdress>Pnei Menachem 1 Petach Tikwa</CustomerAdress>
    <CreateOrderDate>2015-07-09T20:26:16</CreateOrderDate>
    <ShippingDate>2015-07-17T20:26:16</ShippingDate>
    <DeliveryDate>2023-02-26T14:47:34.0757983+02:00</DeliveryDate>
  </Order>
  <Order>
    <ID>1013</ID>
    <CustomerName>Naftali Kempeh</CustomerName>
    <CustomerEmail>NaftaliKempeh@gmail.com</CustomerEmail>
    <CustomerAdress>Hadekel 16 Tel Aviv</CustomerAdress>
    <CreateOrderDate>2019-01-18T06:17:14</CreateOrderDate>
    <ShippingDate>2019-01-27T06:17:14</ShippingDate>
    <DeliveryDate>2023-02-26T14:47:36.0805947+02:00</DeliveryDate>
  </Order>
  <Order>
    <ID>1014</ID>
    <CustomerName>Motti Weiss</CustomerName>
    <CustomerEmail>MottiWeiss@gmail.com</CustomerEmail>
    <CustomerAdress>Chazon Ish 3 Beit Shemesh</CustomerAdress>
    <CreateOrderDate>2000-12-20T17:21:38</CreateOrderDate>
    <ShippingDate>2000-12-25T17:21:38</ShippingDate>
    <DeliveryDate>2023-02-26T14:47:07.9107862+02:00</DeliveryDate>
  </Order>
  <Order>
    <ID>1015</ID>
    <CustomerName>Moshe Feld</CustomerName>
    <CustomerEmail>MosheFeld@gmail.com</CustomerEmail>
    <CustomerAdress>Rabbi Akiva 170 Bnei Brak</CustomerAdress>
    <CreateOrderDate>2013-03-04T13:40:02</CreateOrderDate>
    <ShippingDate>2013-03-11T13:40:02</ShippingDate>
    <DeliveryDate>2023-02-26T14:47:31.2907327+02:00</DeliveryDate>
  </Order>
  <Order>
    <ID>1016</ID>
    <CustomerName>Itzik Orlev</CustomerName>
    <CustomerEmail>ItzikOrlev@gmail.com</CustomerEmail>
    <CustomerAdress>Hakalanit 17 herzelia</CustomerAdress>
    <CreateOrderDate>2012-04-10T08:28:34</CreateOrderDate>
    <ShippingDate>2012-04-15T08:28:34</ShippingDate>
    <DeliveryDate>2023-02-26T14:47:24.8111538+02:00</DeliveryDate>
  </Order>
  <Order>
    <ID>1017</ID>
    <CustomerName>Ruli Dikman</CustomerName>
    <CustomerEmail>RuliDikman@gmail.com</CustomerEmail>
    <CustomerAdress>Haturim 6 Jerusalem</CustomerAdress>
    <CreateOrderDate>2021-01-23T04:57:04</CreateOrderDate>
    <ShippingDate>2023-02-26T14:47:37.8325963+02:00</ShippingDate>
    <DeliveryDate>2023-02-26T14:55:03.142586+02:00</DeliveryDate>
  </Order>
  <Order>
    <ID>1018</ID>
    <CustomerName>Ari Hill</CustomerName>
    <CustomerEmail>AriHill@gmail.com</CustomerEmail>
    <CustomerAdress>Malchei Israel 40 Jerusalem</CustomerAdress>
    <CreateOrderDate>2003-02-26T11:49:45</CreateOrderDate>
    <ShippingDate>2023-02-26T14:47:14.6725393+02:00</ShippingDate>
    <DeliveryDate>2023-02-26T14:54:51.2864138+02:00</DeliveryDate>
  </Order>
  <Order>
    <ID>1019</ID>
    <CustomerName>Shuli Rand</CustomerName>
    <CustomerEmail>ShuliRand@gmail.com</CustomerEmail>
    <CustomerAdress>miron 20 Bnei Brak</CustomerAdress>
    <CreateOrderDate>2005-05-05T15:02:16</CreateOrderDate>
    <ShippingDate>2023-02-26T14:47:20.0746406+02:00</ShippingDate>
    <DeliveryDate>2023-02-26T14:54:58.0426522+02:00</DeliveryDate>
  </Order>
  <Order>
    <ID>1020</ID>
    <CustomerName>Ishay Ribo</CustomerName>
    <CustomerEmail>IshayRibo@gmail.com</CustomerEmail>
    <CustomerAdress>Hameiri 4 Jerusalem</CustomerAdress>
    <CreateOrderDate>2008-09-07T21:27:46</CreateOrderDate>
    <ShippingDate>2023-02-26T14:47:20.1148735+02:00</ShippingDate>
    <DeliveryDate>2023-02-26T14:55:02.5826714+02:00</DeliveryDate>
  </Order>
</ArrayOfOrder>